[
  {
    "Codename": "Curie",
    "IDs": [
      { "Vendor": "0x10de", "Device": "0x0040" },
      { "Vendor": "0x10de", "Device": "0x00f0" },
      { "Vendor": "0x10de", "Device": "0x0220" },
      { "Vendor": "0x10de", "Device": "0x0140" },
      { "Vendor": "0x10de", "Device": "0x0160" },
      { "Vendor": "0x10de", "Device": "0x0090" },
      { "Vendor": "0x10de", "Device": "0x01d0" },
      { "Vendor": "0x10de", "Device": "0x0390" },
      { "Vendor": "0x10de", "Device": "0x0290" }
    ]
  },
  {
    "Codename": "Tesla",
    "IDs": [
      { "Vendor": "0x10de", "Device": "0x0190" },
      { "Vendor": "0x10de", "Device": "0x0191" },
      { "Vendor": "0x10de", "Device": "0x0193" },
      { "Vendor": "0x10de", "Device": "0x0194" },
      { "Vendor": "0x10de", "Device": "0x019e" },
      { "Vendor": "0x10de", "Device": "0x019d" },
      { "Vendor": "0x10de", "Device": "0x0400" },
      { "Vendor": "0x10de", "Device": "0x0401" },
      { "Vendor": "0x10de", "Device": "0x0402" },
      { "Vendor": "0x10de", "Device": "0x0403" },
      { "Vendor": "0x10de", "Device": "0x0404" },
      { "Vendor": "0x10de", "Device": "0x0405" },
      { "Vendor": "0x10de", "Device": "0x0406" },
      { "Vendor": "0x10de", "Device": "0x0407" },
      { "Vendor": "0x10de", "Device": "0x0408" },
      { "Vendor": "0x10de", "Device": "0x0409" },
      { "Vendor": "0x10de", "Device": "0x040a" },
      { "Vendor": "0x10de", "Device": "0x040b" },
      { "Vendor": "0x10de", "Device": "0x040c" },
      { "Vendor": "0x10de", "Device": "0x040d" },
      { "Vendor": "0x10de", "Device": "0x040e" },
      { "Vendor": "0x10de", "Device": "0x040f" },
      { "Vendor": "0x10de", "Device": "0x0420" },
      { "Vendor": "0x10de", "Device": "0x0421" },
      { "Vendor": "0x10de", "Device": "0x0422" },
      { "Vendor": "0x10de", "Device": "0x0423" },
      { "Vendor": "0x10de", "Device": "0x0424" },
      { "Vendor": "0x10de", "Device": "0x0425" },
      { "Vendor": "0x10de", "Device": "0x0426" },
      { "Vendor": "0x10de", "Device": "0x0427" },
      { "Vendor": "0x10de", "Device": "0x0428" },
      { "Vendor": "0x10de", "Device": "0x0429" },
      { "Vendor": "0x10de", "Device": "0x042a" },
      { "Vendor": "0x10de", "Device": "0x042b" },
      { "Vendor": "0x10de", "Device": "0x042c" },
      { "Vendor": "0x10de", "Device": "0x042d" },
      { "Vendor": "0x10de", "Device": "0x042e" },
      { "Vendor": "0x10de", "Device": "0x042f" },
      { "Vendor": "0x10de", "Device": "0x0410" },
      { "Vendor": "0x10de", "Device": "0x0600" },
      { "Vendor": "0x10de", "Device": "0x0601" },
      { "Vendor": "0x10de", "Device": "0x0602" },
      { "Vendor": "0x10de", "Device": "0x0603" },
      { "Vendor": "0x10de", "Device": "0x0604" },
      { "Vendor": "0x10de", "Device": "0x0605" },
      { "Vendor": "0x10de", "Device": "0x0606" },
      { "Vendor": "0x10de", "Device": "0x0607" },
      { "Vendor": "0x10de", "Device": "0x0608" },
      { "Vendor": "0x10de", "Device": "0x0609" },
      { "Vendor": "0x10de", "Device": "0x060a" },
      { "Vendor": "0x10de", "Device": "0x060b" },
      { "Vendor": "0x10de", "Device": "0x060c" },
      { "Vendor": "0x10de", "Device": "0x060f" },
      { "Vendor": "0x10de", "Device": "0x0610" },
      { "Vendor": "0x10de", "Device": "0x0611" },
      { "Vendor": "0x10de", "Device": "0x0612" },
      { "Vendor": "0x10de", "Device": "0x0613" },
      { "Vendor": "0x10de", "Device": "0x0614" },
      { "Vendor": "0x10de", "Device": "0x0615" },
      { "Vendor": "0x10de", "Device": "0x0617" },
      { "Vendor": "0x10de", "Device": "0x0618" },
      { "Vendor": "0x10de", "Device": "0x0619" },
      { "Vendor": "0x10de", "Device": "0x061a" },
      { "Vendor": "0x10de", "Device": "0x061b" },
      { "Vendor": "0x10de", "Device": "0x061c" },
      { "Vendor": "0x10de", "Device": "0x061d" },
      { "Vendor": "0x10de", "Device": "0x061e" },
      { "Vendor": "0x10de", "Device": "0x061f" },
      { "Vendor": "0x10de", "Device": "0x0621" },
      { "Vendor": "0x10de", "Device": "0x0622" },
      { "Vendor": "0x10de", "Device": "0x0623" },
      { "Vendor": "0x10de", "Device": "0x0624" },
      { "Vendor": "0x10de", "Device": "0x0625" },
      { "Vendor": "0x10de", "Device": "0x0626" },
      { "Vendor": "0x10de", "Device": "0x0627" },
      { "Vendor": "0x10de", "Device": "0x0628" },
      { "Vendor": "0x10de", "Device": "0x062a" },
      { "Vendor": "0x10de", "Device": "0x062b" },
      { "Vendor": "0x10de", "Device": "0x062c" },
      { "Vendor": "0x10de", "Device": "0x062d" },
      { "Vendor": "0x10de", "Device": "0x062e" },
      { "Vendor": "0x10de", "Device": "0x062f" },
      { "Vendor": "0x10de", "Device": "0x0631" },
      { "Vendor": "0x10de", "Device": "0x0635" },
      { "Vendor": "0x10de", "Device": "0x0637" },
      { "Vendor": "0x10de", "Device": "0x0638" },
      { "Vendor": "0x10de", "Device": "0x063a" },
      { "Vendor": "0x10de", "Device": "0x0640" },
      { "Vendor": "0x10de", "Device": "0x0641" },
      { "Vendor": "0x10de", "Device": "0x0643" },
      { "Vendor": "0x10de", "Device": "0x0644" },
      { "Vendor": "0x10de", "Device": "0x0645" },
      { "Vendor": "0x10de", "Device": "0x0646" },
      { "Vendor": "0x10de", "Device": "0x0647" },
      { "Vendor": "0x10de", "Device": "0x0648" },
      { "Vendor": "0x10de", "Device": "0x0649" },
      { "Vendor": "0x10de", "Device": "0x064a" },
      { "Vendor": "0x10de", "Device": "0x064b" },
      { "Vendor": "0x10de", "Device": "0x064c" },
      { "Vendor": "0x10de", "Device": "0x0651" },
      { "Vendor": "0x10de", "Device": "0x0652" },
      { "Vendor": "0x10de", "Device": "0x0653" },
      { "Vendor": "0x10de", "Device": "0x0654" },
      { "Vendor": "0x10de", "Device": "0x0655" },
      { "Vendor": "0x10de", "Device": "0x0656" },
      { "Vendor": "0x10de", "Device": "0x0658" },
      { "Vendor": "0x10de", "Device": "0x0659" },
      { "Vendor": "0x10de", "Device": "0x065a" },
      { "Vendor": "0x10de", "Device": "0x065b" },
      { "Vendor": "0x10de", "Device": "0x065c" },
      { "Vendor": "0x10de", "Device": "0x065f" },
      { "Vendor": "0x10de", "Device": "0x06e0" },
      { "Vendor": "0x10de", "Device": "0x06e1" },
      { "Vendor": "0x10de", "Device": "0x06e2" },
      { "Vendor": "0x10de", "Device": "0x06e3" },
      { "Vendor": "0x10de", "Device": "0x06e4" },
      { "Vendor": "0x10de", "Device": "0x06e5" },
      { "Vendor": "0x10de", "Device": "0x06e6" },
      { "Vendor": "0x10de", "Device": "0x06e7" },
      { "Vendor": "0x10de", "Device": "0x06e8" },
      { "Vendor": "0x10de", "Device": "0x06e9" },
      { "Vendor": "0x10de", "Device": "0x06ea" },
      { "Vendor": "0x10de", "Device": "0x06eb" },
      { "Vendor": "0x10de", "Device": "0x06ec" },
      { "Vendor": "0x10de", "Device": "0x06ed" },
      { "Vendor": "0x10de", "Device": "0x06ef" },
      { "Vendor": "0x10de", "Device": "0x06f1" },
      { "Vendor": "0x10de", "Device": "0x06f8" },
      { "Vendor": "0x10de", "Device": "0x06f9" },
      { "Vendor": "0x10de", "Device": "0x06fa" },
      { "Vendor": "0x10de", "Device": "0x06fb" },
      { "Vendor": "0x10de", "Device": "0x06fd" },
      { "Vendor": "0x10de", "Device": "0x06ff" },
      { "Vendor": "0x10de", "Device": "0x05e0" },
      { "Vendor": "0x10de", "Device": "0x05e1" },
      { "Vendor": "0x10de", "Device": "0x05e2" },
      { "Vendor": "0x10de", "Device": "0x05e3" },
      { "Vendor": "0x10de", "Device": "0x05e6" },
      { "Vendor": "0x10de", "Device": "0x05e7" },
      { "Vendor": "0x10de", "Device": "0x05e9" },
      { "Vendor": "0x10de", "Device": "0x05ea" },
      { "Vendor": "0x10de", "Device": "0x05eb" },
      { "Vendor": "0x10de", "Device": "0x05ed" },
      { "Vendor": "0x10de", "Device": "0x05ee" },
      { "Vendor": "0x10de", "Device": "0x05ef" },
      { "Vendor": "0x10de", "Device": "0x05fd" },
      { "Vendor": "0x10de", "Device": "0x05fe" },
      { "Vendor": "0x10de", "Device": "0x05ff" },
      { "Vendor": "0x10de", "Device": "0x0840" },
      { "Vendor": "0x10de", "Device": "0x0844" },
      { "Vendor": "0x10de", "Device": "0x0845" },
      { "Vendor": "0x10de", "Device": "0x0846" },
      { "Vendor": "0x10de", "Device": "0x0847" },
      { "Vendor": "0x10de", "Device": "0x0848" },
      { "Vendor": "0x10de", "Device": "0x0849" },
      { "Vendor": "0x10de", "Device": "0x084a" },
      { "Vendor": "0x10de", "Device": "0x084b" },
      { "Vendor": "0x10de", "Device": "0x084c" },
      { "Vendor": "0x10de", "Device": "0x084d" },
      { "Vendor": "0x10de", "Device": "0x084f" },
      { "Vendor": "0x10de", "Device": "0x0860" },
      { "Vendor": "0x10de", "Device": "0x0861" },
      { "Vendor": "0x10de", "Device": "0x0862" },
      { "Vendor": "0x10de", "Device": "0x0863" },
      { "Vendor": "0x10de", "Device": "0x0864" },
      { "Vendor": "0x10de", "Device": "0x0865" },
      { "Vendor": "0x10de", "Device": "0x0866" },
      { "Vendor": "0x10de", "Device": "0x0867" },
      { "Vendor": "0x10de", "Device": "0x0868" },
      { "Vendor": "0x10de", "Device": "0x0869" },
      { "Vendor": "0x10de", "Device": "0x086a" },
      { "Vendor": "0x10de", "Device": "0x086c" },
      { "Vendor": "0x10de", "Device": "0x086d" },
      { "Vendor": "0x10de", "Device": "0x086e" },
      { "Vendor": "0x10de", "Device": "0x086f" },
      { "Vendor": "0x10de", "Device": "0x0870" },
      { "Vendor": "0x10de", "Device": "0x0871" },
      { "Vendor": "0x10de", "Device": "0x0872" },
      { "Vendor": "0x10de", "Device": "0x0873" },
      { "Vendor": "0x10de", "Device": "0x0874" },
      { "Vendor": "0x10de", "Device": "0x0876" },
      { "Vendor": "0x10de", "Device": "0x087a" },
      { "Vendor": "0x10de", "Device": "0x087d" },
      { "Vendor": "0x10de", "Device": "0x087e" },
      { "Vendor": "0x10de", "Device": "0x087f" },
      { "Vendor": "0x10de", "Device": "0x0ca0" },
      { "Vendor": "0x10de", "Device": "0x0ca2" },
      { "Vendor": "0x10de", "Device": "0x0ca3" },
      { "Vendor": "0x10de", "Device": "0x0ca4" },
      { "Vendor": "0x10de", "Device": "0x0ca5" },
      { "Vendor": "0x10de", "Device": "0x0ca7" },
      { "Vendor": "0x10de", "Device": "0x0ca9" },
      { "Vendor": "0x10de", "Device": "0x0cac" },
      { "Vendor": "0x10de", "Device": "0x0caf" },
      { "Vendor": "0x10de", "Device": "0x0cb0" },
      { "Vendor": "0x10de", "Device": "0x0cb1" },
      { "Vendor": "0x10de", "Device": "0x0cbc" },
      { "Vendor": "0x10de", "Device": "0x0a20" },
      { "Vendor": "0x10de", "Device": "0x0a22" },
      { "Vendor": "0x10de", "Device": "0x0a23" },
      { "Vendor": "0x10de", "Device": "0x0a26" },
      { "Vendor": "0x10de", "Device": "0x0a27" },
      { "Vendor": "0x10de", "Device": "0x0a28" },
      { "Vendor": "0x10de", "Device": "0x0a29" },
      { "Vendor": "0x10de", "Device": "0x0a2a" },
      { "Vendor": "0x10de", "Device": "0x0a2b" },
      { "Vendor": "0x10de", "Device": "0x0a2c" },
      { "Vendor": "0x10de", "Device": "0x0a2d" },
      { "Vendor": "0x10de", "Device": "0x0a32" },
      { "Vendor": "0x10de", "Device": "0x0a34" },
      { "Vendor": "0x10de", "Device": "0x0a35" },
      { "Vendor": "0x10de", "Device": "0x0a38" },
      { "Vendor": "0x10de", "Device": "0x0a3c" },
      { "Vendor": "0x10de", "Device": "0x0a60" },
      { "Vendor": "0x10de", "Device": "0x0a62" },
      { "Vendor": "0x10de", "Device": "0x0a63" },
      { "Vendor": "0x10de", "Device": "0x0a64" },
      { "Vendor": "0x10de", "Device": "0x0a65" },
      { "Vendor": "0x10de", "Device": "0x0a66" },
      { "Vendor": "0x10de", "Device": "0x0a67" },
      { "Vendor": "0x10de", "Device": "0x0a68" },
      { "Vendor": "0x10de", "Device": "0x0a69" },
      { "Vendor": "0x10de", "Device": "0x0a6a" },
      { "Vendor": "0x10de", "Device": "0x0a6c" },
      { "Vendor": "0x10de", "Device": "0x0a6e" },
      { "Vendor": "0x10de", "Device": "0x0a6f" },
      { "Vendor": "0x10de", "Device": "0x0a70" },
      { "Vendor": "0x10de", "Device": "0x0a71" },
      { "Vendor": "0x10de", "Device": "0x0a72" },
      { "Vendor": "0x10de", "Device": "0x0a73" },
      { "Vendor": "0x10de", "Device": "0x0a74" },
      { "Vendor": "0x10de", "Device": "0x0a75" },
      { "Vendor": "0x10de", "Device": "0x0a76" },
      { "Vendor": "0x10de", "Device": "0x0a78" },
      { "Vendor": "0x10de", "Device": "0x0a7a" },
      { "Vendor": "0x10de", "Device": "0x0a7c" },
      { "Vendor": "0x10de", "Device": "0x10c0" },
      { "Vendor": "0x10de", "Device": "0x10c3" },
      { "Vendor": "0x10de", "Device": "0x10c5" },
      { "Vendor": "0x10de", "Device": "0x10d8" },
      { "Vendor": "0x10de", "Device": "0x08a0" },
      { "Vendor": "0x10de", "Device": "0x08a2" },
      { "Vendor": "0x10de", "Device": "0x08a3" },
      { "Vendor": "0x10de", "Device": "0x08a4" }
    ]
  },
  {
    "Codename": "Fermi",
    "IDs": [
      { "Vendor": "0x10de", "Device": "0x06c0" },
      { "Vendor": "0x10de", "Device": "0x06c4" },
      { "Vendor": "0x10de", "Device": "0x06ca" },
      { "Vendor": "0x10de", "Device": "0x06cb" },
      { "Vendor": "0x10de", "Device": "0x06cd" },
      { "Vendor": "0x10de", "Device": "0x06d1" },
      { "Vendor": "0x10de", "Device": "0x06d2" },
      { "Vendor": "0x10de", "Device": "0x06d8" },
      { "Vendor": "0x10de", "Device": "0x06d9" },
      { "Vendor": "0x10de", "Device": "0x06da" },
      { "Vendor": "0x10de", "Device": "0x06dc" },
      { "Vendor": "0x10de", "Device": "0x06dd" },
      { "Vendor": "0x10de", "Device": "0x06de" },
      { "Vendor": "0x10de", "Device": "0x06df" },
      { "Vendor": "0x10de", "Device": "0x0e22" },
      { "Vendor": "0x10de", "Device": "0x0e23" },
      { "Vendor": "0x10de", "Device": "0x0e24" },
      { "Vendor": "0x10de", "Device": "0x0e30" },
      { "Vendor": "0x10de", "Device": "0x0e31" },
      { "Vendor": "0x10de", "Device": "0x0e3a" },
      { "Vendor": "0x10de", "Device": "0x0e3b" },
      { "Vendor": "0x10de", "Device": "0x1200" },
      { "Vendor": "0x10de", "Device": "0x1201" },
      { "Vendor": "0x10de", "Device": "0x1202" },
      { "Vendor": "0x10de", "Device": "0x1203" },
      { "Vendor": "0x10de", "Device": "0x1205" },
      { "Vendor": "0x10de", "Device": "0x1206" },
      { "Vendor": "0x10de", "Device": "0x1207" },
      { "Vendor": "0x10de", "Device": "0x1208" },
      { "Vendor": "0x10de", "Device": "0x1210" },
      { "Vendor": "0x10de", "Device": "0x1211" },
      { "Vendor": "0x10de", "Device": "0x1212" },
      { "Vendor": "0x10de", "Device": "0x1213" },
      { "Vendor": "0x10de", "Device": "0x0dc0" },
      { "Vendor": "0x10de", "Device": "0x0dc4" },
      { "Vendor": "0x10de", "Device": "0x0dc5" },
      { "Vendor": "0x10de", "Device": "0x0dc6" },
      { "Vendor": "0x10de", "Device": "0x0dcd" },
      { "Vendor": "0x10de", "Device": "0x0dce" },
      { "Vendor": "0x10de", "Device": "0x0dd1" },
      { "Vendor": "0x10de", "Device": "0x0dd2" },
      { "Vendor": "0x10de", "Device": "0x0dd3" },
      { "Vendor": "0x10de", "Device": "0x0dd6" },
      { "Vendor": "0x10de", "Device": "0x0dd8" },
      { "Vendor": "0x10de", "Device": "0x0dda" },
      { "Vendor": "0x10de", "Device": "0x1241" },
      { "Vendor": "0x10de", "Device": "0x1243" },
      { "Vendor": "0x10de", "Device": "0x1244" },
      { "Vendor": "0x10de", "Device": "0x1245" },
      { "Vendor": "0x10de", "Device": "0x1246" },
      { "Vendor": "0x10de", "Device": "0x1247" },
      { "Vendor": "0x10de", "Device": "0x1248" },
      { "Vendor": "0x10de", "Device": "0x1249" },
      { "Vendor": "0x10de", "Device": "0x124b" },
      { "Vendor": "0x10de", "Device": "0x124d" },
      { "Vendor": "0x10de", "Device": "0x1251" },
      { "Vendor": "0x10de", "Device": "0x0de0" },
      { "Vendor": "0x10de", "Device": "0x0de1" },
      { "Vendor": "0x10de", "Device": "0x0de2" },
      { "Vendor": "0x10de", "Device": "0x0de3" },
      { "Vendor": "0x10de", "Device": "0x0de4" },
      { "Vendor": "0x10de", "Device": "0x0de5" },
      { "Vendor": "0x10de", "Device": "0x0de8" },
      { "Vendor": "0x10de", "Device": "0x0de9" },
      { "Vendor": "0x10de", "Device": "0x0dea" },
      { "Vendor": "0x10de", "Device": "0x0deb" },
      { "Vendor": "0x10de", "Device": "0x0dec" },
      { "Vendor": "0x10de", "Device": "0x0ded" },
      { "Vendor": "0x10de", "Device": "0x0dee" },
      { "Vendor": "0x10de", "Device": "0x0def" },
      { "Vendor": "0x10de", "Device": "0x0df0" },
      { "Vendor": "0x10de", "Device": "0x0df1" },
      { "Vendor": "0x10de", "Device": "0x0df2" },
      { "Vendor": "0x10de", "Device": "0x0df3" },
      { "Vendor": "0x10de", "Device": "0x0df4" },
      { "Vendor": "0x10de", "Device": "0x0df5" },
      { "Vendor": "0x10de", "Device": "0x0df6" },
      { "Vendor": "0x10de", "Device": "0x0df7" },
      { "Vendor": "0x10de", "Device": "0x0df8" },
      { "Vendor": "0x10de", "Device": "0x0df9" },
      { "Vendor": "0x10de", "Device": "0x0dfa" },
      { "Vendor": "0x10de", "Device": "0x0dfc" },
      { "Vendor": "0x10de", "Device": "0x0f00" },
      { "Vendor": "0x10de", "Device": "0x0f01" },
      { "Vendor": "0x10de", "Device": "0x0f02" },
      { "Vendor": "0x10de", "Device": "0x1080" },
      { "Vendor": "0x10de", "Device": "0x1081" },
      { "Vendor": "0x10de", "Device": "0x1082" },
      { "Vendor": "0x10de", "Device": "0x1084" },
      { "Vendor": "0x10de", "Device": "0x1086" },
      { "Vendor": "0x10de", "Device": "0x1087" },
      { "Vendor": "0x10de", "Device": "0x1088" },
      { "Vendor": "0x10de", "Device": "0x1089" },
      { "Vendor": "0x10de", "Device": "0x108b" },
      { "Vendor": "0x10de", "Device": "0x1091" },
      { "Vendor": "0x10de", "Device": "0x1096" },
      { "Vendor": "0x10de", "Device": "0x109a" },
      { "Vendor": "0x10de", "Device": "0x109b" },
      { "Vendor": "0x10de", "Device": "0x1040" },
      { "Vendor": "0x10de", "Device": "0x1042" },
      { "Vendor": "0x10de", "Device": "0x1048" },
      { "Vendor": "0x10de", "Device": "0x1049" },
      { "Vendor": "0x10de", "Device": "0x104a" },
      { "Vendor": "0x10de", "Device": "0x104b" },
      { "Vendor": "0x10de", "Device": "0x104c" },
      { "Vendor": "0x10de", "Device": "0x1050" },
      { "Vendor": "0x10de", "Device": "0x1051" },
      { "Vendor": "0x10de", "Device": "0x1052" },
      { "Vendor": "0x10de", "Device": "0x1054" },
      { "Vendor": "0x10de", "Device": "0x1055" },
      { "Vendor": "0x10de", "Device": "0x1056" },
      { "Vendor": "0x10de", "Device": "0x1057" },
      { "Vendor": "0x10de", "Device": "0x1058" },
      { "Vendor": "0x10de", "Device": "0x1059" },
      { "Vendor": "0x10de", "Device": "0x105a" },
      { "Vendor": "0x10de", "Device": "0x105b" },
      { "Vendor": "0x10de", "Device": "0x107c" },
      { "Vendor": "0x10de", "Device": "0x107d" },
      { "Vendor": "0x10de", "Device": "0x1140" }
    ]
  },
  {
    "Codename": "Kepler",
    "IDs": [
      { "Vendor": "0x10de", "Device": "0x1180" },
      { "Vendor": "0x10de", "Device": "0x1183" },
      { "Vendor": "0x10de", "Device": "0x1184" },
      { "Vendor": "0x10de", "Device": "0x1185" },
      { "Vendor": "0x10de", "Device": "0x1186" },
      { "Vendor": "0x10de", "Device": "0x1187" },
      { "Vendor": "0x10de", "Device": "0x1188" },
      { "Vendor": "0x10de", "Device": "0x1189" },
      { "Vendor": "0x10de", "Device": "0x118e" },
      { "Vendor": "0x10de", "Device": "0x118f" },
      { "Vendor": "0x10de", "Device": "0x1198" },
      { "Vendor": "0x10de", "Device": "0x1199" },
      { "Vendor": "0x10de", "Device": "0x119a" },
      { "Vendor": "0x10de", "Device": "0x119d" },
      { "Vendor": "0x10de", "Device": "0x119e" },
      { "Vendor": "0x10de", "Device": "0x119f" },
      { "Vendor": "0x10de", "Device": "0x11a0" },
      { "Vendor": "0x10de", "Device": "0x11a1" },
      { "Vendor": "0x10de", "Device": "0x11a2" },
      { "Vendor": "0x10de", "Device": "0x11a3" },
      { "Vendor": "0x10de", "Device": "0x11a7" },
      { "Vendor": "0x10de", "Device": "0x11a9" },
      { "Vendor": "0x10de", "Device": "0x11b4" },
      { "Vendor": "0x10de", "Device": "0x11b6" },
      { "Vendor": "0x10de", "Device": "0x11b7" },
      { "Vendor": "0x10de", "Device": "0x11b8" },
      { "Vendor": "0x10de", "Device": "0x11ba" },
      { "Vendor": "0x10de", "Device": "0x11bc" },
      { "Vendor": "0x10de", "Device": "0x11bd" },
      { "Vendor": "0x10de", "Device": "0x11be" },
      { "Vendor": "0x10de", "Device": "0x11bf" },
      { "Vendor": "0x10de", "Device": "0x11c0" },
      { "Vendor": "0x10de", "Device": "0x11c2" },
      { "Vendor": "0x10de", "Device": "0x11c6" },
      { "Vendor": "0x10de", "Device": "0x11e0" },
      { "Vendor": "0x10de", "Device": "0x11e1" },
      { "Vendor": "0x10de", "Device": "0x11e2" },
      { "Vendor": "0x10de", "Device": "0x11fa" },
      { "Vendor": "0x10de", "Device": "0x11fc" },
      { "Vendor": "0x10de", "Device": "0x0fc0" },
      { "Vendor": "0x10de", "Device": "0x0fc1" },
      { "Vendor": "0x10de", "Device": "0x0fc2" },
      { "Vendor": "0x10de", "Device": "0x0fc6" },
      { "Vendor": "0x10de", "Device": "0x0fc8" },
      { "Vendor": "0x10de", "Device": "0x0fcd" },
      { "Vendor": "0x10de", "Device": "0x0fd1" },
      { "Vendor": "0x10de", "Device": "0x0fd2" },
      { "Vendor": "0x10de", "Device": "0x0fd3" },
      { "Vendor": "0x10de", "Device": "0x0fd4" },
      { "Vendor": "0x10de", "Device": "0x0fd5" },
      { "Vendor": "0x10de", "Device": "0x0fd8" },
      { "Vendor": "0x10de", "Device": "0x0fd9" },
      { "Vendor": "0x10de", "Device": "0x0fdf" },
      { "Vendor": "0x10de", "Device": "0x0fe0" },
      { "Vendor": "0x10de", "Device": "0x0fe1" },
      { "Vendor": "0x10de", "Device": "0x0fe3" },
      { "Vendor": "0x10de", "Device": "0x0fe4" },
      { "Vendor": "0x10de", "Device": "0x0fe9" },
      { "Vendor": "0x10de", "Device": "0x0fea" },
      { "Vendor": "0x10de", "Device": "0x0fee" },
      { "Vendor": "0x10de", "Device": "0x0ff2" },
      { "Vendor": "0x10de", "Device": "0x0ff3" },
      { "Vendor": "0x10de", "Device": "0x0ff6" },
      { "Vendor": "0x10de", "Device": "0x0ff9" },
      { "Vendor": "0x10de", "Device": "0x0ffa" },
      { "Vendor": "0x10de", "Device": "0x0ffb" },
      { "Vendor": "0x10de", "Device": "0x0ffc" },
      { "Vendor": "0x10de", "Device": "0x0ffd" },
      { "Vendor": "0x10de", "Device": "0x0ffe" },
      { "Vendor": "0x10de", "Device": "0x0fff" },
      { "Vendor": "0x10de", "Device": "0x1001" },
      { "Vendor": "0x10de", "Device": "0x1003" },
      { "Vendor": "0x10de", "Device": "0x1004" },
      { "Vendor": "0x10de", "Device": "0x1005" },
      { "Vendor": "0x10de", "Device": "0x1007" },
      { "Vendor": "0x10de", "Device": "0x100a" },
      { "Vendor": "0x10de", "Device": "0x100c" },
      { "Vendor": "0x10de", "Device": "0x101f" },
      { "Vendor": "0x10de", "Device": "0x1020" },
      { "Vendor": "0x10de", "Device": "0x1021" },
      { "Vendor": "0x10de", "Device": "0x1022" },
      { "Vendor": "0x10de", "Device": "0x1023" },
      { "Vendor": "0x10de", "Device": "0x1024" },
      { "Vendor": "0x10de", "Device": "0x1026" },
      { "Vendor": "0x10de", "Device": "0x1028" },
      { "Vendor": "0x10de", "Device": "0x102d" },
      { "Vendor": "0x10de", "Device": "0x103c" },
      { "Vendor": "0x10de", "Device": "0x1280" },
      { "Vendor": "0x10de", "Device": "0x1281" },
      { "Vendor": "0x10de", "Device": "0x1282" },
      { "Vendor": "0x10de", "Device": "0x1284" },
      { "Vendor": "0x10de", "Device": "0x1286" },
      { "Vendor": "0x10de", "Device": "0x1287" },
      { "Vendor": "0x10de", "Device": "0x1288" },
      { "Vendor": "0x10de", "Device": "0x1289" },
      { "Vendor": "0x10de", "Device": "0x128b" },
      { "Vendor": "0x10de", "Device": "0x1290" },
      { "Vendor": "0x10de", "Device": "0x1291" },
      { "Vendor": "0x10de", "Device": "0x1292" },
      { "Vendor": "0x10de", "Device": "0x1293" },
      { "Vendor": "0x10de", "Device": "0x1294" },
      { "Vendor": "0x10de", "Device": "0x1295" },
      { "Vendor": "0x10de", "Device": "0x1296" },
      { "Vendor": "0x10de", "Device": "0x1298" },
      { "Vendor": "0x10de", "Device": "0x1299" },
      { "Vendor": "0x10de", "Device": "0x129a" },
      { "Vendor": "0x10de", "Device": "0x12b9" },
      { "Vendor": "0x10de", "Device": "0x12ba" }
    ]
  }
]
